seasondh/__init__.py
seasondh/base.py
seasondh/dataset.py
seasondh/interfaces.py
seasondh/kernel.py
seasondh/storage.py
seasondh/version.py
seasondh-0.1.1.dist-info/METADATA
seasondh-0.1.1.dist-info/WHEEL
seasondh-0.1.1.dist-info/top_level.txt
seasondh-0.1.1.dist-info/RECORD
