Metadata-Version: 2.1
Name: seasondh
Version: 0.1.1
Summary: season datahub platform
Home-page: https://github.com/season-framework/seasondh
Author: proin
Author-email: proin@season.co.kr
License: MIT
Platform: UNKNOWN
Classifier: License :: OSI Approved :: MIT License
Requires-Python: >=3.6
